{
  "Packages": {
    "OpenNGS.NPC.Common": {
      "Name": "OpenNGS.NPC.Common",
      "ModelPackage": "OpenNGS.NPC.Common",
      "PackageType": "Message",
      "Scope": "All",
      "Models": {
        "OpenNGS.NPC.Common.NPC_UIBIND": {
          "RawPackage": "OpenNGS.NPC.Common",
          "Methods": {},
          "Name": "NPC_UIBIND",
          "Package": "OpenNGS.NPC.Common",
          "Fullname": "OpenNGS.NPC.Common.NPC_UIBIND",
          "PackageName": "OpenNGS.NPC.Common.NPC_UIBIND",
          "Description": "NPC绑定系统",
          "Tag": 0,
          "Flag": 0,
          "Scope": "All",
          "ModelType": "None",
          "Type": "Enum",
          "Entity": {
            "Name": "NPC_UIBIND",
            "Package": "OpenNGS.NPC",
            "Namespcae": "OpenNGS.NPC.Common",
            "Fullname": "OpenNGS.NPC.Common.NPC_UIBIND",
            "Type": 0,
            "Description": "Data\\Entities\\OpenNGS\\OpenNGS.NPC.xlsx",
            "Tag": 0,
            "Properties": {
              "NPC_UIBIND_NONE": {
                "Name": "NPC_UIBIND_NONE",
                "Type": "Uint32",
                "Description": "无",
                "Tag": 0,
                "Scope": "All",
                "Attributes": "None",
                "IsRepeated": false
              },
              "NPC_UIBIND_ROLE": {
                "Name": "NPC_UIBIND_ROLE",
                "Type": "Uint32",
                "Description": "角色系统",
                "Tag": 2,
                "Scope": "All",
                "Attributes": "None",
                "IsRepeated": false
              },
              "NPC_UIBIND_HANDBOOK": {
                "Name": "NPC_UIBIND_HANDBOOK",
                "Type": "Uint32",
                "Description": "图鉴系统",
                "Tag": 7,
                "Scope": "All",
                "Attributes": "None",
                "IsRepeated": false
              },
              "NPC_UIBIND_ACHIEVEMENT": {
                "Name": "NPC_UIBIND_ACHIEVEMENT",
                "Type": "Uint32",
                "Description": "成就系统",
                "Tag": 6,
                "Scope": "All",
                "Attributes": "None",
                "IsRepeated": false
              },
              "NPC_UIBIND_RECORD": {
                "Name": "NPC_UIBIND_RECORD",
                "Type": "Uint32",
                "Description": "战绩系统",
                "Tag": 9,
                "Scope": "All",
                "Attributes": "None",
                "IsRepeated": false
              },
              "NPC_UIBIND_RANK": {
                "Name": "NPC_UIBIND_RANK",
                "Type": "Uint32",
                "Description": "排行榜",
                "Tag": 15,
                "Scope": "All",
                "Attributes": "None",
                "IsRepeated": false
              },
              "NPC_UIBIND_STORE": {
                "Name": "NPC_UIBIND_STORE",
                "Type": "Uint32",
                "Description": "商城系统",
                "Tag": 3,
                "Scope": "All",
                "Attributes": "None",
                "IsRepeated": false
              },
              "NPC_UIBIND_TECHNOLOGY": {
                "Name": "NPC_UIBIND_TECHNOLOGY",
                "Type": "Uint32",
                "Description": "科研系统",
                "Tag": 16,
                "Scope": "All",
                "Attributes": "None",
                "IsRepeated": false
              },
              "NPC_UIBIND_EQUIPBUILD": {
                "Name": "NPC_UIBIND_EQUIPBUILD",
                "Type": "Uint32",
                "Description": "装备系统",
                "Tag": 17,
                "Scope": "All",
                "Attributes": "None",
                "IsRepeated": false
              },
              "NPC_UIBIND_STASH": {
                "Name": "NPC_UIBIND_STASH",
                "Type": "Uint32",
                "Description": "仓库",
                "Tag": 34,
                "Scope": "All",
                "Attributes": "None",
                "IsRepeated": false
              }
            }
          },
          "ModelPackage": "OpenNGS.NPC"
        }
      },
      "References": []
    },
    "OpenNGS.NPC.Data": {
      "Name": "OpenNGS.NPC.Data",
      "ModelPackage": "OpenNGS.NPC.Data",
      "PackageType": "Message",
      "Scope": "All",
      "Models": {
        "OpenNGS.NPC.Data.NPCData": {
          "RawPackage": "OpenNGS.NPC.Data",
          "Methods": {},
          "Name": "NPCData",
          "Package": "OpenNGS.NPC.Data",
          "Fullname": "OpenNGS.NPC.Data.NPCData",
          "PackageName": "OpenNGS.NPC.Data.NPCData",
          "Description": "NPC信息",
          "Tag": 0,
          "Flag": 0,
          "Scope": "All",
          "ModelType": "Table",
          "Type": "Struct",
          "Entity": {
            "Name": "NPCData",
            "Package": "OpenNGS.NPC",
            "Namespcae": "OpenNGS.NPC.Data",
            "Fullname": "OpenNGS.NPC.Data.NPCData",
            "Type": 0,
            "Description": "Data\\Entities\\OpenNGS\\OpenNGS.NPC.xlsx",
            "Tag": 0,
            "Properties": {
              "ID": {
                "Name": "ID",
                "Type": "Uint32",
                "Description": "NPCID",
                "Tag": 1,
                "Scope": "All",
                "Attributes": "Required",
                "IsRepeated": false
              },
              "Name": {
                "Name": "Name",
                "Type": "String",
                "Description": "NPC名字",
                "Tag": 2,
                "Scope": "All",
                "Attributes": "None",
                "IsRepeated": false
              },
              "GameName": {
                "Name": "GameName",
                "Type": "NGSText",
                "CustomType": "NGSText",
                "Description": "NPC在游戏中的名字",
                "Tag": 3,
                "Scope": "All",
                "Attributes": "None",
                "IsRepeated": false
              },
              "PrefabName": {
                "Name": "PrefabName",
                "Type": "String",
                "Description": "NPC预制体",
                "Tag": 4,
                "Scope": "All",
                "Attributes": "None",
                "IsRepeated": false
              },
              "Package": {
                "Name": "Package",
                "Type": "String",
                "Description": "包名",
                "Tag": 5,
                "Scope": "All",
                "Attributes": "None",
                "IsRepeated": false
              },
              "UIID": {
                "Name": "UIID",
                "Type": "Unknow",
                "CustomType": "NPC_UIBIND",
                "Description": "UI功能ID",
                "Tag": 6,
                "Scope": "All",
                "Attributes": "Repeated",
                "IsRepeated": true
              },
              "DialogIDs": {
                "Name": "DialogIDs",
                "Type": "Uint32",
                "Description": "NPC对话ids",
                "Tag": 7,
                "Scope": "All",
                "Attributes": "Repeated",
                "IsRepeated": true
              }
            }
          },
          "ModelPackage": "OpenNGS.NPC"
        }
      },
      "References": [
        "OpenNGS.Core",
        "OpenNGS.NPC.Common"
      ]
    }
  },
  "Name": "OpenNGS.NPC",
  "PackageFile": "Packages/OpenNGS.NPC.json"
}